ossimg/__init__.py
ossimg/core.py
ossimg/template.py
ossimg-2.0.0.dist-info/licenses/LICENSE
tests/__init__.py
tests/test_core.py
ossimg-2.0.0.dist-info/METADATA
ossimg-2.0.0.dist-info/WHEEL
ossimg-2.0.0.dist-info/top_level.txt
ossimg-2.0.0.dist-info/RECORD
